grafanapy/__init__.py
grafanapy/echarts.py
grafanapy/server.py
grafanapy-0.2.0.dist-info/METADATA
grafanapy-0.2.0.dist-info/WHEEL
grafanapy-0.2.0.dist-info/top_level.txt
grafanapy-0.2.0.dist-info/RECORD
