Metadata-Version: 2.1
Name: grafanapy
Version: 0.2.0
Summary: Serve pandas DataFrames as Grafana-compatible JSON APIs
Author: Aref Farzaneh
Classifier: Programming Language :: Python :: 3
Classifier: Operating System :: OS Independent
Requires-Python: >=3.7
Requires-Dist: fastapi
Requires-Dist: uvicorn
Requires-Dist: pandas
